hmcfg/__init__.py
hmcfg/loader.py
hmcfg/simplematch.py
hmcfg-0.0.1.dist-info/LICENSE
hmcfg-0.0.1.dist-info/METADATA
hmcfg-0.0.1.dist-info/WHEEL
hmcfg-0.0.1.dist-info/top_level.txt
hmcfg-0.0.1.dist-info/RECORD
