Metadata-Version: 2.1
Name: hmcfg
Version: 0.0.1
Summary: Hierarchical and Metadata Configuration loader and validator
Author-email: Grzegorz Rusin <grzegorz.rusin@databricks.com>
Project-URL: Homepage, https://github.com/grusin-db/hmcfg
Project-URL: Bug Tracker, https://github.com/grusin-db/hmcfg/issues
Classifier: Programming Language :: Python :: 3
Classifier: License :: OSI Approved :: Apache Software License
Classifier: Operating System :: OS Independent
Requires-Python: >=3.8
License-File: LICENSE
